{
	"name": "QuestionTemplates",
	"properties": {
		"linkedServiceName": {
			"referenceName": "SQLDataWarehouseDevAuth",
			"type": "LinkedServiceReference"
		},
		"annotations": [],
		"type": "AzureSqlTable",
		"schema": [
			{
				"name": "id",
				"type": "varchar"
			},
			{
				"name": "internal_id",
				"type": "varchar"
			},
			{
				"name": "help",
				"type": "nvarchar"
			},
			{
				"name": "title",
				"type": "nvarchar"
			},
			{
				"name": "required",
				"type": "bit"
			},
			{
				"name": "type",
				"type": "nvarchar"
			},
			{
				"name": "config",
				"type": "nvarchar"
			},
			{
				"name": "category",
				"type": "nvarchar"
			},
			{
				"name": "created_at",
				"type": "datetimeoffset",
				"scale": 7
			},
			{
				"name": "modified_at",
				"type": "datetimeoffset",
				"scale": 7
			},
			{
				"name": "entity_source",
				"type": "nvarchar"
			}
		],
		"typeProperties": {
			"schema": "dbo",
			"table": "QuestionTemplates"
		}
	}
}